py_perf_event-0.2.0.dist-info/METADATA
py_perf_event-0.2.0.dist-info/WHEEL
py_perf_event-0.2.0.dist-info/license_files/LICENSE
py_perf_event/__init__.py
py_perf_event/py_perf_event.abi3.so
py_perf_event-0.2.0.dist-info/RECORD
